terminalforms/__init__.py
terminalforms/forms.py
terminalforms-1.2.dist-info/LICENSE
terminalforms-1.2.dist-info/METADATA
terminalforms-1.2.dist-info/WHEEL
terminalforms-1.2.dist-info/top_level.txt
terminalforms-1.2.dist-info/RECORD
