Metadata-Version: 2.1
Name: terminalforms
Version: 1.2
Summary: Add forms to your terminal applications
Home-page: https://github.com/W1L7dev/TerminalForms
Author: W1L7dev
Author-email: w1l7dev@gmail.com
License: MIT
Requires-Python: >=3.6
License-File: LICENSE
Requires-Dist: inquirer (==3.1.3)
